indi_pylibcamera/CameraControl.py
indi_pylibcamera/SnoopingManager.py
indi_pylibcamera/__init__.py
indi_pylibcamera/indi_pylibcamera.ini
indi_pylibcamera/indi_pylibcamera.py
indi_pylibcamera/indi_pylibcamera.xml
indi_pylibcamera/indi_pylibcamera2.ini
indi_pylibcamera/indi_pylibcamera2.py
indi_pylibcamera/indi_pylibcamera2.xml
indi_pylibcamera/indi_pylibcamera3.ini
indi_pylibcamera/indi_pylibcamera3.py
indi_pylibcamera/indi_pylibcamera3.xml
indi_pylibcamera/indi_pylibcamera4.ini
indi_pylibcamera/indi_pylibcamera4.py
indi_pylibcamera/indi_pylibcamera4.xml
indi_pylibcamera/indi_pylibcamera5.ini
indi_pylibcamera/indi_pylibcamera5.py
indi_pylibcamera/indi_pylibcamera5.xml
indi_pylibcamera/indi_pylibcamera_postinstall.py
indi_pylibcamera/indidevice.py
indi_pylibcamera/make_driver_xml.py
indi_pylibcamera/print_camera_information.py
indi_pylibcamera-3.1.0.dist-info/licenses/LICENSE
indi_pylibcamera-3.1.0.dist-info/METADATA
indi_pylibcamera-3.1.0.dist-info/WHEEL
indi_pylibcamera-3.1.0.dist-info/entry_points.txt
indi_pylibcamera-3.1.0.dist-info/top_level.txt
indi_pylibcamera-3.1.0.dist-info/RECORD
