Metadata-Version: 2.4
Name: indi_pylibcamera
Version: 3.1.0
Summary: An INDI driver for Raspberry Pi cameras supported by libcamera
Home-page: https://github.com/scriptorron/indi_pylibcamera
Author: Ronald Schreiber
Author-email: ronald.schreiber01@gmx.de
Requires-Python: >=3.7
License-File: LICENSE
Dynamic: license-file
